cytopix/__init__.py
cytopix/__main__.py
cytopix/_main.py
cytopix/_version.py
cytopix/colorize.py
cytopix/main.py
cytopix/main_ui.py
cytopix/png_io.py
cytopix/seg_session.py
cytopix/splash.py
cytopix/img/__init__.py
cytopix/img/cytopix_icon.png
cytopix-0.2.2.dist-info/licenses/LICENSE
cytopix-0.2.2.dist-info/METADATA
cytopix-0.2.2.dist-info/WHEEL
cytopix-0.2.2.dist-info/entry_points.txt
cytopix-0.2.2.dist-info/top_level.txt
cytopix-0.2.2.dist-info/RECORD
