Metadata-Version: 2.4
Name: cytopix
Version: 0.2.2
Summary: GUI for pixel-based manual segmentation of DC images
Author: Paul Müller
Maintainer-email: Paul Müller <dev@craban.de>
License-Expression: GPL-3.0-or-later
Project-URL: source, https://github.com/DC-Analysis/CytoPix
Project-URL: tracker, https://github.com/DC-Analysis/CytoPix/issues
Project-URL: documentation, https://cytopix.readthedocs.io/en/stable/
Project-URL: changelog, https://cytopix.readthedocs.io/en/stable/sec_changelog.html
Keywords: RT-DC,deformability,cytometry,segmentation
Classifier: Operating System :: OS Independent
Classifier: Programming Language :: Python :: 3
Classifier: Topic :: Scientific/Engineering :: Visualization
Classifier: Intended Audience :: Science/Research
Requires-Python: <4,>=3.12
License-File: LICENSE
Requires-Dist: dclab
Requires-Dist: dcnum>=0.27.1
Requires-Dist: h5py<4,>=3.0.0
Requires-Dist: numpy<3,>=1.21
Requires-Dist: pillow
Requires-Dist: pyqt6
Requires-Dist: pyqtgraph
Requires-Dist: scikit-image
Requires-Dist: scipy
Requires-Dist: torch>=2.2
Dynamic: license-file
